im_jote-0.11.3.dist-info/licenses/LICENSE
jote/VERSION
jote/__init__.py
jote/__main__.py
jote/compose.py
jote/jote.py
jote/jote.yamllint
im_jote-0.11.3.dist-info/METADATA
im_jote-0.11.3.dist-info/WHEEL
im_jote-0.11.3.dist-info/entry_points.txt
im_jote-0.11.3.dist-info/top_level.txt
im_jote-0.11.3.dist-info/RECORD
