Metadata-Version: 2.4
Name: im-jote
Version: 0.11.3
Summary: The IM Data Manager Job Tester (jote)
Home-page: https://github.com/informaticsmatters/squonk2-data-manager-job-tester
Author: Alan Christie
Author-email: achristie@informaticsmatters.com
License: MIT
Keywords: configuration
Platform: any
Classifier: Development Status :: 5 - Production/Stable
Classifier: Environment :: Console
Classifier: Intended Audience :: Developers
Classifier: License :: OSI Approved :: MIT License
Classifier: Programming Language :: Python :: 3.11
Classifier: Programming Language :: Python :: 3.12
Classifier: Programming Language :: Python :: 3.13
Classifier: Topic :: System :: Installation/Setup
Classifier: Operating System :: POSIX :: Linux
Requires-Python: >=3.10.0
License-File: LICENSE
Requires-Dist: im-data-manager-job-decoder==2.5.0
Requires-Dist: munch==2.5.0
Requires-Dist: wheel==0.40.0
Requires-Dist: yamllint==1.37.1
Requires-Dist: setuptools>=70.0.0
Requires-Dist: pyyaml==5.3.1
Dynamic: author
Dynamic: author-email
Dynamic: classifier
Dynamic: description
Dynamic: home-page
Dynamic: keywords
Dynamic: license
Dynamic: license-file
Dynamic: platform
Dynamic: requires-dist
Dynamic: requires-python
Dynamic: summary
